aiozmq/__init__.py
aiozmq/_test_util.py
aiozmq/core.py
aiozmq/interface.py
aiozmq/log.py
aiozmq/selector.py
aiozmq/stream.py
aiozmq/util.py
aiozmq/cli/__init__.py
aiozmq/cli/proxy.py
aiozmq/rpc/__init__.py
aiozmq/rpc/base.py
aiozmq/rpc/log.py
aiozmq/rpc/packer.py
aiozmq/rpc/pipeline.py
aiozmq/rpc/pubsub.py
aiozmq/rpc/rpc.py
aiozmq/rpc/util.py
aiozmq-1.0.0.dist-info/LICENSE
aiozmq-1.0.0.dist-info/METADATA
aiozmq-1.0.0.dist-info/WHEEL
aiozmq-1.0.0.dist-info/entry_points.txt
aiozmq-1.0.0.dist-info/top_level.txt
aiozmq-1.0.0.dist-info/RECORD
