Metadata-Version: 2.1
Name: aiozmq
Version: 1.0.0
Summary: ZeroMQ integration with asyncio.
Home-page: http://aiozmq.readthedocs.org
Download-URL: https://pypi.python.org/pypi/aiozmq
Author: Nikolay Kim
Author-email: fafhrd91@gmail.com
Maintainer: Jelle Zijlstra
Maintainer-email: jelle.zijlstra@gmail.com
License: BSD
Platform: POSIX
Platform: Windows
Platform: MacOS X
Classifier: License :: OSI Approved :: BSD License
Classifier: Intended Audience :: Developers
Classifier: Programming Language :: Python :: 3
Classifier: Programming Language :: Python :: 3.6
Classifier: Programming Language :: Python :: 3.7
Classifier: Programming Language :: Python :: 3.8
Classifier: Programming Language :: Python :: 3.9
Classifier: Programming Language :: Python :: 3.10
Classifier: Programming Language :: Python :: 3.11
Classifier: Operating System :: POSIX
Classifier: Operating System :: MacOS :: MacOS X
Classifier: Operating System :: Microsoft :: Windows
Classifier: Environment :: Web Environment
Classifier: Development Status :: 4 - Beta
Classifier: Framework :: AsyncIO
License-File: LICENSE
Requires-Dist: pyzmq (!=17.1.2,>=13.1)
Provides-Extra: rpc
Requires-Dist: msgpack (>=0.5.0) ; extra == 'rpc'
